catbox_sdk/__init__.py
catbox_sdk/base.py
catbox_sdk/catbox.py
catbox_sdk/exceptions.py
catbox_sdk/littlebox.py
catbox_sdk-0.1.0.dist-info/METADATA
catbox_sdk-0.1.0.dist-info/WHEEL
catbox_sdk-0.1.0.dist-info/RECORD
