Metadata-Version: 2.1
Name: catbox-sdk
Version: 0.1.0
Summary: 
Author: jeremy
Author-email: nguyentruong.xyz0405@gmail.com
Requires-Python: >=3.12,<4.0
Classifier: Programming Language :: Python :: 3
Classifier: Programming Language :: Python :: 3.12
Classifier: Programming Language :: Python :: 3.13
Requires-Dist: requests (>=2.32.3,<3.0.0)
Requires-Dist: requests-toolbelt (>=1.0.0,<2.0.0)
